Workbook

Sheet EMI Calculator
A1: Loan EMI Calculator
A2: Enter loan details in blue cells. All calculations update automatically.
A4: LOAN INPUTS
A5: Loan Amount | B5: 500000 | C5: Principal amount of the loan
A6: Annual Interest Rate (%) | B6: 0.105 | C6: Enter as decimal e.g. 10.5% → 0.105 OR just 10.5
A7: Loan Tenure (Months) | B7: 60 | C7: Number of monthly instalments
A8: Start Date | B8: 2025-01-01 | C8: Loan disbursement date
A10: CALCULATED RESULTS
A11: Monthly EMI (₹) | B11: =IFERROR(PMT(B6/12,B7,-B5),0)
A12: Total Amount Payable (₹) | B12: =IFERROR(B11*B7,0)
A13: Total Interest Payable (₹) | B13: =IFERROR(B12-B5,0)
A14: Interest as % of Principal | B14: =IFERROR(B13/B5,0)
A16: Navneet Priye Chauhan — Finance & Operations Consultant | Free Template: Loan EMI Calculator

Sheet Amortization Schedule
A1: Loan Amortization Schedule
A3: # | B3: Payment Date | C3: Opening Balance (₹) | D3: EMI (₹) | E3: Principal (₹) | F3: Interest (₹) | G3: Closing Balance (₹) | H3: Cumul. Interest (₹) | I3: Cumul. Principal (₹)
A4: 1 | B4: ='EMI Calculator'!B8 | C4: ='EMI Calculator'!B5 | D4: ='EMI Calculator'!B11 | E4: =IFERROR(D4-F4,0) | F4: =IFERROR(C4*'EMI Calculator'!B6/12,0) | G4: =IFERROR(C4-E4,0) | H4: =F4 | I4: =E4
A5: 2 | B5: =IFERROR(DATE(YEAR(B4),MONTH(B4)+1,DAY(B4)),"") | C5: =IFERROR(IF(A5<='EMI Calculator'!B7,G4,""),"") | D5: =IFERROR(IF(A5<='EMI Calculator'!B7,'EMI Calculator'!B11,""),"") | E5: =IFERROR(IF(A5<='EMI Calculator'!B7,D5-F5,""),"") | F5: =IFERROR(IF(A5<='EMI Calculator'!B7,C5*'EMI Calculator'!B6/12,""),"") | G5: =IFERROR(IF(A5<='EMI Calculator'!B7,MAX(C5-E5,0),""),"") | H5: =IFERROR(IF(A5<='EMI Calculator'!B7,H4+F5,""),"") | I5: =IFERROR(IF(A5<='EMI Calculator'!B7,I4+E5,""),"")
A6: 3 | B6: =IFERROR(DATE(YEAR(B5),MONTH(B5)+1,DAY(B5)),"") | C6: =IFERROR(IF(A6<='EMI Calculator'!B7,G5,""),"") | D6: =IFERROR(IF(A6<='EMI Calculator'!B7,'EMI Calculator'!B11,""),"") | E6: =IFERROR(IF(A6<='EMI Calculator'!B7,D6-F6,""),"") | F6: =IFERROR(IF(A6<='EMI Calculator'!B7,C6*'EMI Calculator'!B6/12,""),"") | G6: =IFERROR(IF(A6<='EMI Calculator'!B7,MAX(C6-E6,0),""),"") | H6: =IFERROR(IF(A6<='EMI Calculator'!B7,H5+F6,""),"") | I6: =IFERROR(IF(A6<='EMI Calculator'!B7,I5+E6,""),"")
A7: 4 | B7: =IFERROR(DATE(YEAR(B6),MONTH(B6)+1,DAY(B6)),"") | C7: =IFERROR(IF(A7<='EMI Calculator'!B7,G6,""),"") | D7: =IFERROR(IF(A7<='EMI Calculator'!B7,'EMI Calculator'!B11,""),"") | E7: =IFERROR(IF(A7<='EMI Calculator'!B7,D7-F7,""),"") | F7: =IFERROR(IF(A7<='EMI Calculator'!B7,C7*'EMI Calculator'!B6/12,""),"") | G7: =IFERROR(IF(A7<='EMI Calculator'!B7,MAX(C7-E7,0),""),"") | H7: =IFERROR(IF(A7<='EMI Calculator'!B7,H6+F7,""),"") | I7: =IFERROR(IF(A7<='EMI Calculator'!B7,I6+E7,""),"")
A8: 5 | B8: =IFERROR(DATE(YEAR(B7),MONTH(B7)+1,DAY(B7)),"") | C8: =IFERROR(IF(A8<='EMI Calculator'!B7,G7,""),"") | D8: =IFERROR(IF(A8<='EMI Calculator'!B7,'EMI Calculator'!B11,""),"") | E8: =IFERROR(IF(A8<='EMI Calculator'!B7,D8-F8,""),"") | F8: =IFERROR(IF(A8<='EMI Calculator'!B7,C8*'EMI Calculator'!B6/12,""),"") | G8: =IFERROR(IF(A8<='EMI Calculator'!B7,MAX(C8-E8,0),""),"") | H8: =IFERROR(IF(A8<='EMI Calculator'!B7,H7+F8,""),"") | I8: =IFERROR(IF(A8<='EMI Calculator'!B7,I7+E8,""),"")
A9: 6 | B9: =IFERROR(DATE(YEAR(B8),MONTH(B8)+1,DAY(B8)),"") | C9: =IFERROR(IF(A9<='EMI Calculator'!B7,G8,""),"") | D9: =IFERROR(IF(A9<='EMI Calculator'!B7,'EMI Calculator'!B11,""),"") | E9: =IFERROR(IF(A9<='EMI Calculator'!B7,D9-F9,""),"") | F9: =IFERROR(IF(A9<='EMI Calculator'!B7,C9*'EMI Calculator'!B6/12,""),"") | G9: =IFERROR(IF(A9<='EMI Calculator'!B7,MAX(C9-E9,0),""),"") | H9: =IFERROR(IF(A9<='EMI Calculator'!B7,H8+F9,""),"") | I9: =IFERROR(IF(A9<='EMI Calculator'!B7,I8+E9,""),"")
A10: 7 | B10: =IFERROR(DATE(YEAR(B9),MONTH(B9)+1,DAY(B9)),"") | C10: =IFERROR(IF(A10<='EMI Calculator'!B7,G9,""),"") | D10: =IFERROR(IF(A10<='EMI Calculator'!B7,'EMI Calculator'!B11,""),"") | E10: =IFERROR(IF(A10<='EMI Calculator'!B7,D10-F10,""),"") | F10: =IFERROR(IF(A10<='EMI Calculator'!B7,C10*'EMI Calculator'!B6/12,""),"") | G10: =IFERROR(IF(A10<='EMI Calculator'!B7,MAX(C10-E10,0),""),"") | H10: =IFERROR(IF(A10<='EMI Calculator'!B7,H9+F10,""),"") | I10: =IFERROR(IF(A10<='EMI Calculator'!B7,I9+E10,""),"")
A11: 8 | B11: =IFERROR(DATE(YEAR(B10),MONTH(B10)+1,DAY(B10)),"") | C11: =IFERROR(IF(A11<='EMI Calculator'!B7,G10,""),"") | D11: =IFERROR(IF(A11<='EMI Calculator'!B7,'EMI Calculator'!B11,""),"") | E11: =IFERROR(IF(A11<='EMI Calculator'!B7,D11-F11,""),"") | F11: =IFERROR(IF(A11<='EMI Calculator'!B7,C11*'EMI Calculator'!B6/12,""),"") | G11: =IFERROR(IF(A11<='EMI Calculator'!B7,MAX(C11-E11,0),""),"") | H11: =IFERROR(IF(A11<='EMI Calculator'!B7,H10+F11,""),"") | I11: =IFERROR(IF(A11<='EMI Calculator'!B7,I10+E11,""),"")
A12: 9 | B12: =IFERROR(DATE(YEAR(B11),MONTH(B11)+1,DAY(B11)),"") | C12: =IFERROR(IF(A12<='EMI Calculator'!B7,G11,""),"") | D12: =IFERROR(IF(A12<='EMI Calculator'!B7,'EMI Calculator'!B11,""),"") | E12: =IFERROR(IF(A12<='EMI Calculator'!B7,D12-F12,""),"") | F12: =IFERROR(IF(A12<='EMI Calculator'!B7,C12*'EMI Calculator'!B6/12,""),"") | G12: =IFERROR(IF(A12<='EMI Calculator'!B7,MAX(C12-E12,0),""),"") | H12: =IFERROR(IF(A12<='EMI Calculator'!B7,H11+F12,""),"") | I12: =IFERROR(IF(A12<='EMI Calculator'!B7,I11+E12,""),"")
A13: 10 | B13: =IFERROR(DATE(YEAR(B12),MONTH(B12)+1,DAY(B12)),"") | C13: =IFERROR(IF(A13<='EMI Calculator'!B7,G12,""),"") | D13: =IFERROR(IF(A13<='EMI Calculator'!B7,'EMI Calculator'!B11,""),"") | E13: =IFERROR(IF(A13<='EMI Calculator'!B7,D13-F13,""),"") | F13: =IFERROR(IF(A13<='EMI Calculator'!B7,C13*'EMI Calculator'!B6/12,""),"") | G13: =IFERROR(IF(A13<='EMI Calculator'!B7,MAX(C13-E13,0),""),"") | H13: =IFERROR(IF(A13<='EMI Calculator'!B7,H12+F13,""),"") | I13: =IFERROR(IF(A13<='EMI Calculator'!B7,I12+E13,""),"")
A14: 11 | B14: =IFERROR(DATE(YEAR(B13),MONTH(B13)+1,DAY(B13)),"") | C14: =IFERROR(IF(A14<='EMI Calculator'!B7,G13,""),"") | D14: =IFERROR(IF(A14<='EMI Calculator'!B7,'EMI Calculator'!B11,""),"") | E14: =IFERROR(IF(A14<='EMI Calculator'!B7,D14-F14,""),"") | F14: =IFERROR(IF(A14<='EMI Calculator'!B7,C14*'EMI Calculator'!B6/12,""),"") | G14: =IFERROR(IF(A14<='EMI Calculator'!B7,MAX(C14-E14,0),""),"") | H14: =IFERROR(IF(A14<='EMI Calculator'!B7,H13+F14,""),"") | I14: =IFERROR(IF(A14<='EMI Calculator'!B7,I13+E14,""),"")
A15: 12 | B15: =IFERROR(DATE(YEAR(B14),MONTH(B14)+1,DAY(B14)),"") | C15: =IFERROR(IF(A15<='EMI Calculator'!B7,G14,""),"") | D15: =IFERROR(IF(A15<='EMI Calculator'!B7,'EMI Calculator'!B11,""),"") | E15: =IFERROR(IF(A15<='EMI Calculator'!B7,D15-F15,""),"") | F15: =IFERROR(IF(A15<='EMI Calculator'!B7,C15*'EMI Calculator'!B6/12,""),"") | G15: =IFERROR(IF(A15<='EMI Calculator'!B7,MAX(C15-E15,0),""),"") | H15: =IFERROR(IF(A15<='EMI Calculator'!B7,H14+F15,""),"") | I15: =IFERROR(IF(A15<='EMI Calculator'!B7,I14+E15,""),"")
A16: 13 | B16: =IFERROR(DATE(YEAR(B15),MONTH(B15)+1,DAY(B15)),"") | C16: =IFERROR(IF(A16<='EMI Calculator'!B7,G15,""),"") | D16: =IFERROR(IF(A16<='EMI Calculator'!B7,'EMI Calculator'!B11,""),"") | E16: =IFERROR(IF(A16<='EMI Calculator'!B7,D16-F16,""),"") | F16: =IFERROR(IF(A16<='EMI Calculator'!B7,C16*'EMI Calculator'!B6/12,""),"") | G16: =IFERROR(IF(A16<='EMI Calculator'!B7,MAX(C16-E16,0),""),"") | H16: =IFERROR(IF(A16<='EMI Calculator'!B7,H15+F16,""),"") | I16: =IFERROR(IF(A16<='EMI Calculator'!B7,I15+E16,""),"")
A17: 14 | B17: =IFERROR(DATE(YEAR(B16),MONTH(B16)+1,DAY(B16)),"") | C17: =IFERROR(IF(A17<='EMI Calculator'!B7,G16,""),"") | D17: =IFERROR(IF(A17<='EMI Calculator'!B7,'EMI Calculator'!B11,""),"") | E17: =IFERROR(IF(A17<='EMI Calculator'!B7,D17-F17,""),"") | F17: =IFERROR(IF(A17<='EMI Calculator'!B7,C17*'EMI Calculator'!B6/12,""),"") | G17: =IFERROR(IF(A17<='EMI Calculator'!B7,MAX(C17-E17,0),""),"") | H17: =IFERROR(IF(A17<='EMI Calculator'!B7,H16+F17,""),"") | I17: =IFERROR(IF(A17<='EMI Calculator'!B7,I16+E17,""),"")
A18: 15 | B18: =IFERROR(DATE(YEAR(B17),MONTH(B17)+1,DAY(B17)),"") | C18: =IFERROR(IF(A18<='EMI Calculator'!B7,G17,""),"") | D18: =IFERROR(IF(A18<='EMI Calculator'!B7,'EMI Calculator'!B11,""),"") | E18: =IFERROR(IF(A18<='EMI Calculator'!B7,D18-F18,""),"") | F18: =IFERROR(IF(A18<='EMI Calculator'!B7,C18*'EMI Calculator'!B6/12,""),"") | G18: =IFERROR(IF(A18<='EMI Calculator'!B7,MAX(C18-E18,0),""),"") | H18: =IFERROR(IF(A18<='EMI Calculator'!B7,H17+F18,""),"") | I18: =IFERROR(IF(A18<='EMI Calculator'!B7,I17+E18,""),"")
A19: 16 | B19: =IFERROR(DATE(YEAR(B18),MONTH(B18)+1,DAY(B18)),"") | C19: =IFERROR(IF(A19<='EMI Calculator'!B7,G18,""),"") | D19: =IFERROR(IF(A19<='EMI Calculator'!B7,'EMI Calculator'!B11,""),"") | E19: =IFERROR(IF(A19<='EMI Calculator'!B7,D19-F19,""),"") | F19: =IFERROR(IF(A19<='EMI Calculator'!B7,C19*'EMI Calculator'!B6/12,""),"") | G19: =IFERROR(IF(A19<='EMI Calculator'!B7,MAX(C19-E19,0),""),"") | H19: =IFERROR(IF(A19<='EMI Calculator'!B7,H18+F19,""),"") | I19: =IFERROR(IF(A19<='EMI Calculator'!B7,I18+E19,""),"")
A20: 17 | B20: =IFERROR(DATE(YEAR(B19),MONTH(B19)+1,DAY(B19)),"") | C20: =IFERROR(IF(A20<='EMI Calculator'!B7,G19,""),"") | D20: =IFERROR(IF(A20<='EMI Calculator'!B7,'EMI Calculator'!B11,""),"") | E20: =IFERROR(IF(A20<='EMI Calculator'!B7,D20-F20,""),"") | F20: =IFERROR(IF(A20<='EMI Calculator'!B7,C20*'EMI Calculator'!B6/12,""),"") | G20: =IFERROR(IF(A20<='EMI Calculator'!B7,MAX(C20-E20,0),""),"") | H20: =IFERROR(IF(A20<='EMI Calculator'!B7,H19+F20,""),"") | I20: =IFERROR(IF(A20<='EMI Calculator'!B7,I19+E20,""),"")
A21: 18 | B21: =IFERROR(DATE(YEAR(B20),MONTH(B20)+1,DAY(B20)),"") | C21: =IFERROR(IF(A21<='EMI Calculator'!B7,G20,""),"") | D21: =IFERROR(IF(A21<='EMI Calculator'!B7,'EMI Calculator'!B11,""),"") | E21: =IFERROR(IF(A21<='EMI Calculator'!B7,D21-F21,""),"") | F21: =IFERROR(IF(A21<='EMI Calculator'!B7,C21*'EMI Calculator'!B6/12,""),"") | G21: =IFERROR(IF(A21<='EMI Calculator'!B7,MAX(C21-E21,0),""),"") | H21: =IFERROR(IF(A21<='EMI Calculator'!B7,H20+F21,""),"") | I21: =IFERROR(IF(A21<='EMI Calculator'!B7,I20+E21,""),"")
A22: 19 | B22: =IFERROR(DATE(YEAR(B21),MONTH(B21)+1,DAY(B21)),"") | C22: =IFERROR(IF(A22<='EMI Calculator'!B7,G21,""),"") | D22: =IFERROR(IF(A22<='EMI Calculator'!B7,'EMI Calculator'!B11,""),"") | E22: =IFERROR(IF(A22<='EMI Calculator'!B7,D22-F22,""),"") | F22: =IFERROR(IF(A22<='EMI Calculator'!B7,C22*'EMI Calculator'!B6/12,""),"") | G22: =IFERROR(IF(A22<='EMI Calculator'!B7,MAX(C22-E22,0),""),"") | H22: =IFERROR(IF(A22<='EMI Calculator'!B7,H21+F22,""),"") | I22: =IFERROR(IF(A22<='EMI Calculator'!B7,I21+E22,""),"")
A23: 20 | B23: =IFERROR(DATE(YEAR(B22),MONTH(B22)+1,DAY(B22)),"") | C23: =IFERROR(IF(A23<='EMI Calculator'!B7,G22,""),"") | D23: =IFERROR(IF(A23<='EMI Calculator'!B7,'EMI Calculator'!B11,""),"") | E23: =IFERROR(IF(A23<='EMI Calculator'!B7,D23-F23,""),"") | F23: =IFERROR(IF(A23<='EMI Calculator'!B7,C23*'EMI Calculator'!B6/12,""),"") | G23: =IFERROR(IF(A23<='EMI Calculator'!B7,MAX(C23-E23,0),""),"") | H23: =IFERROR(IF(A23<='EMI Calculator'!B7,H22+F23,""),"") | I23: =IFERROR(IF(A23<='EMI Calculator'!B7,I22+E23,""),"")
A24: 21 | B24: =IFERROR(DATE(YEAR(B23),MONTH(B23)+1,DAY(B23)),"") | C24: =IFERROR(IF(A24<='EMI Calculator'!B7,G23,""),"") | D24: =IFERROR(IF(A24<='EMI Calculator'!B7,'EMI Calculator'!B11,""),"") | E24: =IFERROR(IF(A24<='EMI Calculator'!B7,D24-F24,""),"") | F24: =IFERROR(IF(A24<='EMI Calculator'!B7,C24*'EMI Calculator'!B6/12,""),"") | G24: =IFERROR(IF(A24<='EMI Calculator'!B7,MAX(C24-E24,0),""),"") | H24: =IFERROR(IF(A24<='EMI Calculator'!B7,H23+F24,""),"") | I24: =IFERROR(IF(A24<='EMI Calculator'!B7,I23+E24,""),"")
A25: 22 | B25: =IFERROR(DATE(YEAR(B24),MONTH(B24)+1,DAY(B24)),"") | C25: =IFERROR(IF(A25<='EMI Calculator'!B7,G24,""),"") | D25: =IFERROR(IF(A25<='EMI Calculator'!B7,'EMI Calculator'!B11,""),"") | E25: =IFERROR(IF(A25<='EMI Calculator'!B7,D25-F25,""),"") | F25: =IFERROR(IF(A25<='EMI Calculator'!B7,C25*'EMI Calculator'!B6/12,""),"") | G25: =IFERROR(IF(A25<='EMI Calculator'!B7,MAX(C25-E25,0),""),"") | H25: =IFERROR(IF(A25<='EMI Calculator'!B7,H24+F25,""),"") | I25: =IFERROR(IF(A25<='EMI Calculator'!B7,I24+E25,""),"")
A26: 23 | B26: =IFERROR(DATE(YEAR(B25),MONTH(B25)+1,DAY(B25)),"") | C26: =IFERROR(IF(A26<='EMI Calculator'!B7,G25,""),"") | D26: =IFERROR(IF(A26<='EMI Calculator'!B7,'EMI Calculator'!B11,""),"") | E26: =IFERROR(IF(A26<='EMI Calculator'!B7,D26-F26,""),"") | F26: =IFERROR(IF(A26<='EMI Calculator'!B7,C26*'EMI Calculator'!B6/12,""),"") | G26: =IFERROR(IF(A26<='EMI Calculator'!B7,MAX(C26-E26,0),""),"") | H26: =IFERROR(IF(A26<='EMI Calculator'!B7,H25+F26,""),"") | I26: =IFERROR(IF(A26<='EMI Calculator'!B7,I25+E26,""),"")
A27: 24 | B27: =IFERROR(DATE(YEAR(B26),MONTH(B26)+1,DAY(B26)),"") | C27: =IFERROR(IF(A27<='EMI Calculator'!B7,G26,""),"") | D27: =IFERROR(IF(A27<='EMI Calculator'!B7,'EMI Calculator'!B11,""),"") | E27: =IFERROR(IF(A27<='EMI Calculator'!B7,D27-F27,""),"") | F27: =IFERROR(IF(A27<='EMI Calculator'!B7,C27*'EMI Calculator'!B6/12,""),"") | G27: =IFERROR(IF(A27<='EMI Calculator'!B7,MAX(C27-E27,0),""),"") | H27: =IFERROR(IF(A27<='EMI Calculator'!B7,H26+F27,""),"") | I27: =IFERROR(IF(A27<='EMI Calculator'!B7,I26+E27,""),"")
A28: 25 | B28: =IFERROR(DATE(YEAR(B27),MONTH(B27)+1,DAY(B27)),"") | C28: =IFERROR(IF(A28<='EMI Calculator'!B7,G27,""),"") | D28: =IFERROR(IF(A28<='EMI Calculator'!B7,'EMI Calculator'!B11,""),"") | E28: =IFERROR(IF(A28<='EMI Calculator'!B7,D28-F28,""),"") | F28: =IFERROR(IF(A28<='EMI Calculator'!B7,C28*'EMI Calculator'!B6/12,""),"") | G28: =IFERROR(IF(A28<='EMI Calculator'!B7,MAX(C28-E28,0),""),"") | H28: =IFERROR(IF(A28<='EMI Calculator'!B7,H27+F28,""),"") | I28: =IFERROR(IF(A28<='EMI Calculator'!B7,I27+E28,""),"")
A29: 26 | B29: =IFERROR(DATE(YEAR(B28),MONTH(B28)+1,DAY(B28)),"") | C29: =IFERROR(IF(A29<='EMI Calculator'!B7,G28,""),"") | D29: =IFERROR(IF(A29<='EMI Calculator'!B7,'EMI Calculator'!B11,""),"") | E29: =IFERROR(IF(A29<='EMI Calculator'!B7,D29-F29,""),"") | F29: =IFERROR(IF(A29<='EMI Calculator'!B7,C29*'EMI Calculator'!B6/12,""),"") | G29: =IFERROR(IF(A29<='EMI Calculator'!B7,MAX(C29-E29,0),""),"") | H29: =IFERROR(IF(A29<='EMI Calculator'!B7,H28+F29,""),"") | I29: =IFERROR(IF(A29<='EMI Calculator'!B7,I28+E29,""),"")
A30: 27 | B30: =IFERROR(DATE(YEAR(B29),MONTH(B29)+1,DAY(B29)),"") | C30: =IFERROR(IF(A30<='EMI Calculator'!B7,G29,""),"") | D30: =IFERROR(IF(A30<='EMI Calculator'!B7,'EMI Calculator'!B11,""),"") | E30: =IFERROR(IF(A30<='EMI Calculator'!B7,D30-F30,""),"") | F30: =IFERROR(IF(A30<='EMI Calculator'!B7,C30*'EMI Calculator'!B6/12,""),"") | G30: =IFERROR(IF(A30<='EMI Calculator'!B7,MAX(C30-E30,0),""),"") | H30: =IFERROR(IF(A30<='EMI Calculator'!B7,H29+F30,""),"") | I30: =IFERROR(IF(A30<='EMI Calculator'!B7,I29+E30,""),"")
A31: 28 | B31: =IFERROR(DATE(YEAR(B30),MONTH(B30)+1,DAY(B30)),"") | C31: =IFERROR(IF(A31<='EMI Calculator'!B7,G30,""),"") | D31: =IFERROR(IF(A31<='EMI Calculator'!B7,'EMI Calculator'!B11,""),"") | E31: =IFERROR(IF(A31<='EMI Calculator'!B7,D31-F31,""),"") | F31: =IFERROR(IF(A31<='EMI Calculator'!B7,C31*'EMI Calculator'!B6/12,""),"") | G31: =IFERROR(IF(A31<='EMI Calculator'!B7,MAX(C31-E31,0),""),"") | H31: =IFERROR(IF(A31<='EMI Calculator'!B7,H30+F31,""),"") | I31: =IFERROR(IF(A31<='EMI Calculator'!B7,I30+E31,""),"")
A32: 29 | B32: =IFERROR(DATE(YEAR(B31),MONTH(B31)+1,DAY(B31)),"") | C32: =IFERROR(IF(A32<='EMI Calculator'!B7,G31,""),"") | D32: =IFERROR(IF(A32<='EMI Calculator'!B7,'EMI Calculator'!B11,""),"") | E32: =IFERROR(IF(A32<='EMI Calculator'!B7,D32-F32,""),"") | F32: =IFERROR(IF(A32<='EMI Calculator'!B7,C32*'EMI Calculator'!B6/12,""),"") | G32: =IFERROR(IF(A32<='EMI Calculator'!B7,MAX(C32-E32,0),""),"") | H32: =IFERROR(IF(A32<='EMI Calculator'!B7,H31+F32,""),"") | I32: =IFERROR(IF(A32<='EMI Calculator'!B7,I31+E32,""),"")
A33: 30 | B33: =IFERROR(DATE(YEAR(B32),MONTH(B32)+1,DAY(B32)),"") | C33: =IFERROR(IF(A33<='EMI Calculator'!B7,G32,""),"") | D33: =IFERROR(IF(A33<='EMI Calculator'!B7,'EMI Calculator'!B11,""),"") | E33: =IFERROR(IF(A33<='EMI Calculator'!B7,D33-F33,""),"") | F33: =IFERROR(IF(A33<='EMI Calculator'!B7,C33*'EMI Calculator'!B6/12,""),"") | G33: =IFERROR(IF(A33<='EMI Calculator'!B7,MAX(C33-E33,0),""),"") | H33: =IFERROR(IF(A33<='EMI Calculator'!B7,H32+F33,""),"") | I33: =IFERROR(IF(A33<='EMI Calculator'!B7,I32+E33,""),"")
A34: 31 | B34: =IFERROR(DATE(YEAR(B33),MONTH(B33)+1,DAY(B33)),"") | C34: =IFERROR(IF(A34<='EMI Calculator'!B7,G33,""),"") | D34: =IFERROR(IF(A34<='EMI Calculator'!B7,'EMI Calculator'!B11,""),"") | E34: =IFERROR(IF(A34<='EMI Calculator'!B7,D34-F34,""),"") | F34: =IFERROR(IF(A34<='EMI Calculator'!B7,C34*'EMI Calculator'!B6/12,""),"") | G34: =IFERROR(IF(A34<='EMI Calculator'!B7,MAX(C34-E34,0),""),"") | H34: =IFERROR(IF(A34<='EMI Calculator'!B7,H33+F34,""),"") | I34: =IFERROR(IF(A34<='EMI Calculator'!B7,I33+E34,""),"")
A35: 32 | B35: =IFERROR(DATE(YEAR(B34),MONTH(B34)+1,DAY(B34)),"") | C35: =IFERROR(IF(A35<='EMI Calculator'!B7,G34,""),"") | D35: =IFERROR(IF(A35<='EMI Calculator'!B7,'EMI Calculator'!B11,""),"") | E35: =IFERROR(IF(A35<='EMI Calculator'!B7,D35-F35,""),"") | F35: =IFERROR(IF(A35<='EMI Calculator'!B7,C35*'EMI Calculator'!B6/12,""),"") | G35: =IFERROR(IF(A35<='EMI Calculator'!B7,MAX(C35-E35,0),""),"") | H35: =IFERROR(IF(A35<='EMI Calculator'!B7,H34+F35,""),"") | I35: =IFERROR(IF(A35<='EMI Calculator'!B7,I34+E35,""),"")
A36: 33 | B36: =IFERROR(DATE(YEAR(B35),MONTH(B35)+1,DAY(B35)),"") | C36: =IFERROR(IF(A36<='EMI Calculator'!B7,G35,""),"") | D36: =IFERROR(IF(A36<='EMI Calculator'!B7,'EMI Calculator'!B11,""),"") | E36: =IFERROR(IF(A36<='EMI Calculator'!B7,D36-F36,""),"") | F36: =IFERROR(IF(A36<='EMI Calculator'!B7,C36*'EMI Calculator'!B6/12,""),"") | G36: =IFERROR(IF(A36<='EMI Calculator'!B7,MAX(C36-E36,0),""),"") | H36: =IFERROR(IF(A36<='EMI Calculator'!B7,H35+F36,""),"") | I36: =IFERROR(IF(A36<='EMI Calculator'!B7,I35+E36,""),"")
A37: 34 | B37: =IFERROR(DATE(YEAR(B36),MONTH(B36)+1,DAY(B36)),"") | C37: =IFERROR(IF(A37<='EMI Calculator'!B7,G36,""),"") | D37: =IFERROR(IF(A37<='EMI Calculator'!B7,'EMI Calculator'!B11,""),"") | E37: =IFERROR(IF(A37<='EMI Calculator'!B7,D37-F37,""),"") | F37: =IFERROR(IF(A37<='EMI Calculator'!B7,C37*'EMI Calculator'!B6/12,""),"") | G37: =IFERROR(IF(A37<='EMI Calculator'!B7,MAX(C37-E37,0),""),"") | H37: =IFERROR(IF(A37<='EMI Calculator'!B7,H36+F37,""),"") | I37: =IFERROR(IF(A37<='EMI Calculator'!B7,I36+E37,""),"")
A38: 35 | B38: =IFERROR(DATE(YEAR(B37),MONTH(B37)+1,DAY(B37)),"") | C38: =IFERROR(IF(A38<='EMI Calculator'!B7,G37,""),"") | D38: =IFERROR(IF(A38<='EMI Calculator'!B7,'EMI Calculator'!B11,""),"") | E38: =IFERROR(IF(A38<='EMI Calculator'!B7,D38-F38,""),"") | F38: =IFERROR(IF(A38<='EMI Calculator'!B7,C38*'EMI Calculator'!B6/12,""),"") | G38: =IFERROR(IF(A38<='EMI Calculator'!B7,MAX(C38-E38,0),""),"") | H38: =IFERROR(IF(A38<='EMI Calculator'!B7,H37+F38,""),"") | I38: =IFERROR(IF(A38<='EMI Calculator'!B7,I37+E38,""),"")
A39: 36 | B39: =IFERROR(DATE(YEAR(B38),MONTH(B38)+1,DAY(B38)),"") | C39: =IFERROR(IF(A39<='EMI Calculator'!B7,G38,""),"") | D39: =IFERROR(IF(A39<='EMI Calculator'!B7,'EMI Calculator'!B11,""),"") | E39: =IFERROR(IF(A39<='EMI Calculator'!B7,D39-F39,""),"") | F39: =IFERROR(IF(A39<='EMI Calculator'!B7,C39*'EMI Calculator'!B6/12,""),"") | G39: =IFERROR(IF(A39<='EMI Calculator'!B7,MAX(C39-E39,0),""),"") | H39: =IFERROR(IF(A39<='EMI Calculator'!B7,H38+F39,""),"") | I39: =IFERROR(IF(A39<='EMI Calculator'!B7,I38+E39,""),"")
A40: 37 | B40: =IFERROR(DATE(YEAR(B39),MONTH(B39)+1,DAY(B39)),"") | C40: =IFERROR(IF(A40<='EMI Calculator'!B7,G39,""),"") | D40: =IFERROR(IF(A40<='EMI Calculator'!B7,'EMI Calculator'!B11,""),"") | E40: =IFERROR(IF(A40<='EMI Calculator'!B7,D40-F40,""),"") | F40: =IFERROR(IF(A40<='EMI Calculator'!B7,C40*'EMI Calculator'!B6/12,""),"") | G40: =IFERROR(IF(A40<='EMI Calculator'!B7,MAX(C40-E40,0),""),"") | H40: =IFERROR(IF(A40<='EMI Calculator'!B7,H39+F40,""),"") | I40: =IFERROR(IF(A40<='EMI Calculator'!B7,I39+E40,""),"")
A41: 38 | B41: =IFERROR(DATE(YEAR(B40),MONTH(B40)+1,DAY(B40)),"") | C41: =IFERROR(IF(A41<='EMI Calculator'!B7,G40,""),"") | D41: =IFERROR(IF(A41<='EMI Calculator'!B7,'EMI Calculator'!B11,""),"") | E41: =IFERROR(IF(A41<='EMI Calculator'!B7,D41-F41,""),"") | F41: =IFERROR(IF(A41<='EMI Calculator'!B7,C41*'EMI Calculator'!B6/12,""),"") | G41: =IFERROR(IF(A41<='EMI Calculator'!B7,MAX(C41-E41,0),""),"") | H41: =IFERROR(IF(A41<='EMI Calculator'!B7,H40+F41,""),"") | I41: =IFERROR(IF(A41<='EMI Calculator'!B7,I40+E41,""),"")
A42: 39 | B42: =IFERROR(DATE(YEAR(B41),MONTH(B41)+1,DAY(B41)),"") | C42: =IFERROR(IF(A42<='EMI Calculator'!B7,G41,""),"") | D42: =IFERROR(IF(A42<='EMI Calculator'!B7,'EMI Calculator'!B11,""),"") | E42: =IFERROR(IF(A42<='EMI Calculator'!B7,D42-F42,""),"") | F42: =IFERROR(IF(A42<='EMI Calculator'!B7,C42*'EMI Calculator'!B6/12,""),"") | G42: =IFERROR(IF(A42<='EMI Calculator'!B7,MAX(C42-E42,0),""),"") | H42: =IFERROR(IF(A42<='EMI Calculator'!B7,H41+F42,""),"") | I42: =IFERROR(IF(A42<='EMI Calculator'!B7,I41+E42,""),"")
A43: 40 | B43: =IFERROR(DATE(YEAR(B42),MONTH(B42)+1,DAY(B42)),"") | C43: =IFERROR(IF(A43<='EMI Calculator'!B7,G42,""),"") | D43: =IFERROR(IF(A43<='EMI Calculator'!B7,'EMI Calculator'!B11,""),"") | E43: =IFERROR(IF(A43<='EMI Calculator'!B7,D43-F43,""),"") | F43: =IFERROR(IF(A43<='EMI Calculator'!B7,C43*'EMI Calculator'!B6/12,""),"") | G43: =IFERROR(IF(A43<='EMI Calculator'!B7,MAX(C43-E43,0),""),"") | H43: =IFERROR(IF(A43<='EMI Calculator'!B7,H42+F43,""),"") | I43: =IFERROR(IF(A43<='EMI Calculator'!B7,I42+E43,""),"")
A44: 41 | B44: =IFERROR(DATE(YEAR(B43),MONTH(B43)+1,DAY(B43)),"") | C44: =IFERROR(IF(A44<='EMI Calculator'!B7,G43,""),"") | D44: =IFERROR(IF(A44<='EMI Calculator'!B7,'EMI Calculator'!B11,""),"") | E44: =IFERROR(IF(A44<='EMI Calculator'!B7,D44-F44,""),"") | F44: =IFERROR(IF(A44<='EMI Calculator'!B7,C44*'EMI Calculator'!B6/12,""),"") | G44: =IFERROR(IF(A44<='EMI Calculator'!B7,MAX(C44-E44,0),""),"") | H44: =IFERROR(IF(A44<='EMI Calculator'!B7,H43+F44,""),"") | I44: =IFERROR(IF(A44<='EMI Calculator'!B7,I43+E44,""),"")
A45: 42 | B45: =IFERROR(DATE(YEAR(B44),MONTH(B44)+1,DAY(B44)),"") | C45: =IFERROR(IF(A45<='EMI Calculator'!B7,G44,""),"") | D45: =IFERROR(IF(A45<='EMI Calculator'!B7,'EMI Calculator'!B11,""),"") | E45: =IFERROR(IF(A45<='EMI Calculator'!B7,D45-F45,""),"") | F45: =IFERROR(IF(A45<='EMI Calculator'!B7,C45*'EMI Calculator'!B6/12,""),"") | G45: =IFERROR(IF(A45<='EMI Calculator'!B7,MAX(C45-E45,0),""),"") | H45: =IFERROR(IF(A45<='EMI Calculator'!B7,H44+F45,""),"") | I45: =IFERROR(IF(A45<='EMI Calculator'!B7,I44+E45,""),"")
A46: 43 | B46: =IFERROR(DATE(YEAR(B45),MONTH(B45)+1,DAY(B45)),"") | C46: =IFERROR(IF(A46<='EMI Calculator'!B7,G45,""),"") | D46: =IFERROR(IF(A46<='EMI Calculator'!B7,'EMI Calculator'!B11,""),"") | E46: =IFERROR(IF(A46<='EMI Calculator'!B7,D46-F46,""),"") | F46: =IFERROR(IF(A46<='EMI Calculator'!B7,C46*'EMI Calculator'!B6/12,""),"") | G46: =IFERROR(IF(A46<='EMI Calculator'!B7,MAX(C46-E46,0),""),"") | H46: =IFERROR(IF(A46<='EMI Calculator'!B7,H45+F46,""),"") | I46: =IFERROR(IF(A46<='EMI Calculator'!B7,I45+E46,""),"")
A47: 44 | B47: =IFERROR(DATE(YEAR(B46),MONTH(B46)+1,DAY(B46)),"") | C47: =IFERROR(IF(A47<='EMI Calculator'!B7,G46,""),"") | D47: =IFERROR(IF(A47<='EMI Calculator'!B7,'EMI Calculator'!B11,""),"") | E47: =IFERROR(IF(A47<='EMI Calculator'!B7,D47-F47,""),"") | F47: =IFERROR(IF(A47<='EMI Calculator'!B7,C47*'EMI Calculator'!B6/12,""),"") | G47: =IFERROR(IF(A47<='EMI Calculator'!B7,MAX(C47-E47,0),""),"") | H47: =IFERROR(IF(A47<='EMI Calculator'!B7,H46+F47,""),"") | I47: =IFERROR(IF(A47<='EMI Calculator'!B7,I46+E47,""),"")
A48: 45 | B48: =IFERROR(DATE(YEAR(B47),MONTH(B47)+1,DAY(B47)),"") | C48: =IFERROR(IF(A48<='EMI Calculator'!B7,G47,""),"") | D48: =IFERROR(IF(A48<='EMI Calculator'!B7,'EMI Calculator'!B11,""),"") | E48: =IFERROR(IF(A48<='EMI Calculator'!B7,D48-F48,""),"") | F48: =IFERROR(IF(A48<='EMI Calculator'!B7,C48*'EMI Calculator'!B6/12,""),"") | G48: =IFERROR(IF(A48<='EMI Calculator'!B7,MAX(C48-E48,0),""),"") | H48: =IFERROR(IF(A48<='EMI Calculator'!B7,H47+F48,""),"") | I48: =IFERROR(IF(A48<='EMI Calculator'!B7,I47+E48,""),"")
A49: 46 | B49: =IFERROR(DATE(YEAR(B48),MONTH(B48)+1,DAY(B48)),"") | C49: =IFERROR(IF(A49<='EMI Calculator'!B7,G48,""),"") | D49: =IFERROR(IF(A49<='EMI Calculator'!B7,'EMI Calculator'!B11,""),"") | E49: =IFERROR(IF(A49<='EMI Calculator'!B7,D49-F49,""),"") | F49: =IFERROR(IF(A49<='EMI Calculator'!B7,C49*'EMI Calculator'!B6/12,""),"") | G49: =IFERROR(IF(A49<='EMI Calculator'!B7,MAX(C49-E49,0),""),"") | H49: =IFERROR(IF(A49<='EMI Calculator'!B7,H48+F49,""),"") | I49: =IFERROR(IF(A49<='EMI Calculator'!B7,I48+E49,""),"")
A50: 47 | B50: =IFERROR(DATE(YEAR(B49),MONTH(B49)+1,DAY(B49)),"") | C50: =IFERROR(IF(A50<='EMI Calculator'!B7,G49,""),"") | D50: =IFERROR(IF(A50<='EMI Calculator'!B7,'EMI Calculator'!B11,""),"") | E50: =IFERROR(IF(A50<='EMI Calculator'!B7,D50-F50,""),"") | F50: =IFERROR(IF(A50<='EMI Calculator'!B7,C50*'EMI Calculator'!B6/12,""),"") | G50: =IFERROR(IF(A50<='EMI Calculator'!B7,MAX(C50-E50,0),""),"") | H50: =IFERROR(IF(A50<='EMI Calculator'!B7,H49+F50,""),"") | I50: =IFERROR(IF(A50<='EMI Calculator'!B7,I49+E50,""),"")
A51: 48 | B51: =IFERROR(DATE(YEAR(B50),MONTH(B50)+1,DAY(B50)),"") | C51: =IFERROR(IF(A51<='EMI Calculator'!B7,G50,""),"") | D51: =IFERROR(IF(A51<='EMI Calculator'!B7,'EMI Calculator'!B11,""),"") | E51: =IFERROR(IF(A51<='EMI Calculator'!B7,D51-F51,""),"") | F51: =IFERROR(IF(A51<='EMI Calculator'!B7,C51*'EMI Calculator'!B6/12,""),"") | G51: =IFERROR(IF(A51<='EMI Calculator'!B7,MAX(C51-E51,0),""),"") | H51: =IFERROR(IF(A51<='EMI Calculator'!B7,H50+F51,""),"") | I51: =IFERROR(IF(A51<='EMI Calculator'!B7,I50+E51,""),"")
A52: 49 | B52: =IFERROR(DATE(YEAR(B51),MONTH(B51)+1,DAY(B51)),"") | C52: =IFERROR(IF(A52<='EMI Calculator'!B7,G51,""),"") | D52: =IFERROR(IF(A52<='EMI Calculator'!B7,'EMI Calculator'!B11,""),"") | E52: =IFERROR(IF(A52<='EMI Calculator'!B7,D52-F52,""),"") | F52: =IFERROR(IF(A52<='EMI Calculator'!B7,C52*'EMI Calculator'!B6/12,""),"") | G52: =IFERROR(IF(A52<='EMI Calculator'!B7,MAX(C52-E52,0),""),"") | H52: =IFERROR(IF(A52<='EMI Calculator'!B7,H51+F52,""),"") | I52: =IFERROR(IF(A52<='EMI Calculator'!B7,I51+E52,""),"")
A53: 50 | B53: =IFERROR(DATE(YEAR(B52),MONTH(B52)+1,DAY(B52)),"") | C53: =IFERROR(IF(A53<='EMI Calculator'!B7,G52,""),"") | D53: =IFERROR(IF(A53<='EMI Calculator'!B7,'EMI Calculator'!B11,""),"") | E53: =IFERROR(IF(A53<='EMI Calculator'!B7,D53-F53,""),"") | F53: =IFERROR(IF(A53<='EMI Calculator'!B7,C53*'EMI Calculator'!B6/12,""),"") | G53: =IFERROR(IF(A53<='EMI Calculator'!B7,MAX(C53-E53,0),""),"") | H53: =IFERROR(IF(A53<='EMI Calculator'!B7,H52+F53,""),"") | I53: =IFERROR(IF(A53<='EMI Calculator'!B7,I52+E53,""),"")
A54: 51 | B54: =IFERROR(DATE(YEAR(B53),MONTH(B53)+1,DAY(B53)),"") | C54: =IFERROR(IF(A54<='EMI Calculator'!B7,G53,""),"") | D54: =IFERROR(IF(A54<='EMI Calculator'!B7,'EMI Calculator'!B11,""),"") | E54: =IFERROR(IF(A54<='EMI Calculator'!B7,D54-F54,""),"") | F54: =IFERROR(IF(A54<='EMI Calculator'!B7,C54*'EMI Calculator'!B6/12,""),"") | G54: =IFERROR(IF(A54<='EMI Calculator'!B7,MAX(C54-E54,0),""),"") | H54: =IFERROR(IF(A54<='EMI Calculator'!B7,H53+F54,""),"") | I54: =IFERROR(IF(A54<='EMI Calculator'!B7,I53+E54,""),"")
A55: 52 | B55: =IFERROR(DATE(YEAR(B54),MONTH(B54)+1,DAY(B54)),"") | C55: =IFERROR(IF(A55<='EMI Calculator'!B7,G54,""),"") | D55: =IFERROR(IF(A55<='EMI Calculator'!B7,'EMI Calculator'!B11,""),"") | E55: =IFERROR(IF(A55<='EMI Calculator'!B7,D55-F55,""),"") | F55: =IFERROR(IF(A55<='EMI Calculator'!B7,C55*'EMI Calculator'!B6/12,""),"") | G55: =IFERROR(IF(A55<='EMI Calculator'!B7,MAX(C55-E55,0),""),"") | H55: =IFERROR(IF(A55<='EMI Calculator'!B7,H54+F55,""),"") | I55: =IFERROR(IF(A55<='EMI Calculator'!B7,I54+E55,""),"")
A56: 53 | B56: =IFERROR(DATE(YEAR(B55),MONTH(B55)+1,DAY(B55)),"") | C56: =IFERROR(IF(A56<='EMI Calculator'!B7,G55,""),"") | D56: =IFERROR(IF(A56<='EMI Calculator'!B7,'EMI Calculator'!B11,""),"") | E56: =IFERROR(IF(A56<='EMI Calculator'!B7,D56-F56,""),"") | F56: =IFERROR(IF(A56<='EMI Calculator'!B7,C56*'EMI Calculator'!B6/12,""),"") | G56: =IFERROR(IF(A56<='EMI Calculator'!B7,MAX(C56-E56,0),""),"") | H56: =IFERROR(IF(A56<='EMI Calculator'!B7,H55+F56,""),"") | I56: =IFERROR(IF(A56<='EMI Calculator'!B7,I55+E56,""),"")
A57: 54 | B57: =IFERROR(DATE(YEAR(B56),MONTH(B56)+1,DAY(B56)),"") | C57: =IFERROR(IF(A57<='EMI Calculator'!B7,G56,""),"") | D57: =IFERROR(IF(A57<='EMI Calculator'!B7,'EMI Calculator'!B11,""),"") | E57: =IFERROR(IF(A57<='EMI Calculator'!B7,D57-F57,""),"") | F57: =IFERROR(IF(A57<='EMI Calculator'!B7,C57*'EMI Calculator'!B6/12,""),"") | G57: =IFERROR(IF(A57<='EMI Calculator'!B7,MAX(C57-E57,0),""),"") | H57: =IFERROR(IF(A57<='EMI Calculator'!B7,H56+F57,""),"") | I57: =IFERROR(IF(A57<='EMI Calculator'!B7,I56+E57,""),"")
A58: 55 | B58: =IFERROR(DATE(YEAR(B57),MONTH(B57)+1,DAY(B57)),"") | C58: =IFERROR(IF(A58<='EMI Calculator'!B7,G57,""),"") | D58: =IFERROR(IF(A58<='EMI Calculator'!B7,'EMI Calculator'!B11,""),"") | E58: =IFERROR(IF(A58<='EMI Calculator'!B7,D58-F58,""),"") | F58: =IFERROR(IF(A58<='EMI Calculator'!B7,C58*'EMI Calculator'!B6/12,""),"") | G58: =IFERROR(IF(A58<='EMI Calculator'!B7,MAX(C58-E58,0),""),"") | H58: =IFERROR(IF(A58<='EMI Calculator'!B7,H57+F58,""),"") | I58: =IFERROR(IF(A58<='EMI Calculator'!B7,I57+E58,""),"")
A59: 56 | B59: =IFERROR(DATE(YEAR(B58),MONTH(B58)+1,DAY(B58)),"") | C59: =IFERROR(IF(A59<='EMI Calculator'!B7,G58,""),"") | D59: =IFERROR(IF(A59<='EMI Calculator'!B7,'EMI Calculator'!B11,""),"") | E59: =IFERROR(IF(A59<='EMI Calculator'!B7,D59-F59,""),"") | F59: =IFERROR(IF(A59<='EMI Calculator'!B7,C59*'EMI Calculator'!B6/12,""),"") | G59: =IFERROR(IF(A59<='EMI Calculator'!B7,MAX(C59-E59,0),""),"") | H59: =IFERROR(IF(A59<='EMI Calculator'!B7,H58+F59,""),"") | I59: =IFERROR(IF(A59<='EMI Calculator'!B7,I58+E59,""),"")
A60: 57 | B60: =IFERROR(DATE(YEAR(B59),MONTH(B59)+1,DAY(B59)),"") | C60: =IFERROR(IF(A60<='EMI Calculator'!B7,G59,""),"") | D60: =IFERROR(IF(A60<='EMI Calculator'!B7,'EMI Calculator'!B11,""),"") | E60: =IFERROR(IF(A60<='EMI Calculator'!B7,D60-F60,""),"") | F60: =IFERROR(IF(A60<='EMI Calculator'!B7,C60*'EMI Calculator'!B6/12,""),"") | G60: =IFERROR(IF(A60<='EMI Calculator'!B7,MAX(C60-E60,0),""),"") | H60: =IFERROR(IF(A60<='EMI Calculator'!B7,H59+F60,""),"") | I60: =IFERROR(IF(A60<='EMI Calculator'!B7,I59+E60,""),"")
A61: 58 | B61: =IFERROR(DATE(YEAR(B60),MONTH(B60)+1,DAY(B60)),"") | C61: =IFERROR(IF(A61<='EMI Calculator'!B7,G60,""),"") | D61: =IFERROR(IF(A61<='EMI Calculator'!B7,'EMI Calculator'!B11,""),"") | E61: =IFERROR(IF(A61<='EMI Calculator'!B7,D61-F61,""),"") | F61: =IFERROR(IF(A61<='EMI Calculator'!B7,C61*'EMI Calculator'!B6/12,""),"") | G61: =IFERROR(IF(A61<='EMI Calculator'!B7,MAX(C61-E61,0),""),"") | H61: =IFERROR(IF(A61<='EMI Calculator'!B7,H60+F61,""),"") | I61: =IFERROR(IF(A61<='EMI Calculator'!B7,I60+E61,""),"")
A62: 59 | B62: =IFERROR(DATE(YEAR(B61),MONTH(B61)+1,DAY(B61)),"") | C62: =IFERROR(IF(A62<='EMI Calculator'!B7,G61,""),"") | D62: =IFERROR(IF(A62<='EMI Calculator'!B7,'EMI Calculator'!B11,""),"") | E62: =IFERROR(IF(A62<='EMI Calculator'!B7,D62-F62,""),"") | F62: =IFERROR(IF(A62<='EMI Calculator'!B7,C62*'EMI Calculator'!B6/12,""),"") | G62: =IFERROR(IF(A62<='EMI Calculator'!B7,MAX(C62-E62,0),""),"") | H62: =IFERROR(IF(A62<='EMI Calculator'!B7,H61+F62,""),"") | I62: =IFERROR(IF(A62<='EMI Calculator'!B7,I61+E62,""),"")
A63: 60 | B63: =IFERROR(DATE(YEAR(B62),MONTH(B62)+1,DAY(B62)),"") | C63: =IFERROR(IF(A63<='EMI Calculator'!B7,G62,""),"") | D63: =IFERROR(IF(A63<='EMI Calculator'!B7,'EMI Calculator'!B11,""),"") | E63: =IFERROR(IF(A63<='EMI Calculator'!B7,D63-F63,""),"") | F63: =IFERROR(IF(A63<='EMI Calculator'!B7,C63*'EMI Calculator'!B6/12,""),"") | G63: =IFERROR(IF(A63<='EMI Calculator'!B7,MAX(C63-E63,0),""),"") | H63: =IFERROR(IF(A63<='EMI Calculator'!B7,H62+F63,""),"") | I63: =IFERROR(IF(A63<='EMI Calculator'!B7,I62+E63,""),"")
A64: 61 | B64: =IFERROR(DATE(YEAR(B63),MONTH(B63)+1,DAY(B63)),"") | C64: =IFERROR(IF(A64<='EMI Calculator'!B7,G63,""),"") | D64: =IFERROR(IF(A64<='EMI Calculator'!B7,'EMI Calculator'!B11,""),"") | E64: =IFERROR(IF(A64<='EMI Calculator'!B7,D64-F64,""),"") | F64: =IFERROR(IF(A64<='EMI Calculator'!B7,C64*'EMI Calculator'!B6/12,""),"") | G64: =IFERROR(IF(A64<='EMI Calculator'!B7,MAX(C64-E64,0),""),"") | H64: =IFERROR(IF(A64<='EMI Calculator'!B7,H63+F64,""),"") | I64: =IFERROR(IF(A64<='EMI Calculator'!B7,I63+E64,""),"")
A65: 62 | B65: =IFERROR(DATE(YEAR(B64),MONTH(B64)+1,DAY(B64)),"") | C65: =IFERROR(IF(A65<='EMI Calculator'!B7,G64,""),"") | D65: =IFERROR(IF(A65<='EMI Calculator'!B7,'EMI Calculator'!B11,""),"") | E65: =IFERROR(IF(A65<='EMI Calculator'!B7,D65-F65,""),"") | F65: =IFERROR(IF(A65<='EMI Calculator'!B7,C65*'EMI Calculator'!B6/12,""),"") | G65: =IFERROR(IF(A65<='EMI Calculator'!B7,MAX(C65-E65,0),""),"") | H65: =IFERROR(IF(A65<='EMI Calculator'!B7,H64+F65,""),"") | I65: =IFERROR(IF(A65<='EMI Calculator'!B7,I64+E65,""),"")
A66: 63 | B66: =IFERROR(DATE(YEAR(B65),MONTH(B65)+1,DAY(B65)),"") | C66: =IFERROR(IF(A66<='EMI Calculator'!B7,G65,""),"") | D66: =IFERROR(IF(A66<='EMI Calculator'!B7,'EMI Calculator'!B11,""),"") | E66: =IFERROR(IF(A66<='EMI Calculator'!B7,D66-F66,""),"") | F66: =IFERROR(IF(A66<='EMI Calculator'!B7,C66*'EMI Calculator'!B6/12,""),"") | G66: =IFERROR(IF(A66<='EMI Calculator'!B7,MAX(C66-E66,0),""),"") | H66: =IFERROR(IF(A66<='EMI Calculator'!B7,H65+F66,""),"") | I66: =IFERROR(IF(A66<='EMI Calculator'!B7,I65+E66,""),"")
A67: 64 | B67: =IFERROR(DATE(YEAR(B66),MONTH(B66)+1,DAY(B66)),"") | C67: =IFERROR(IF(A67<='EMI Calculator'!B7,G66,""),"") | D67: =IFERROR(IF(A67<='EMI Calculator'!B7,'EMI Calculator'!B11,""),"") | E67: =IFERROR(IF(A67<='EMI Calculator'!B7,D67-F67,""),"") | F67: =IFERROR(IF(A67<='EMI Calculator'!B7,C67*'EMI Calculator'!B6/12,""),"") | G67: =IFERROR(IF(A67<='EMI Calculator'!B7,MAX(C67-E67,0),""),"") | H67: =IFERROR(IF(A67<='EMI Calculator'!B7,H66+F67,""),"") | I67: =IFERROR(IF(A67<='EMI Calculator'!B7,I66+E67,""),"")
A68: 65 | B68: =IFERROR(DATE(YEAR(B67),MONTH(B67)+1,DAY(B67)),"") | C68: =IFERROR(IF(A68<='EMI Calculator'!B7,G67,""),"") | D68: =IFERROR(IF(A68<='EMI Calculator'!B7,'EMI Calculator'!B11,""),"") | E68: =IFERROR(IF(A68<='EMI Calculator'!B7,D68-F68,""),"") | F68: =IFERROR(IF(A68<='EMI Calculator'!B7,C68*'EMI Calculator'!B6/12,""),"") | G68: =IFERROR(IF(A68<='EMI Calculator'!B7,MAX(C68-E68,0),""),"") | H68: =IFERROR(IF(A68<='EMI Calculator'!B7,H67+F68,""),"") | I68: =IFERROR(IF(A68<='EMI Calculator'!B7,I67+E68,""),"")
A69: 66 | B69: =IFERROR(DATE(YEAR(B68),MONTH(B68)+1,DAY(B68)),"") | C69: =IFERROR(IF(A69<='EMI Calculator'!B7,G68,""),"") | D69: =IFERROR(IF(A69<='EMI Calculator'!B7,'EMI Calculator'!B11,""),"") | E69: =IFERROR(IF(A69<='EMI Calculator'!B7,D69-F69,""),"") | F69: =IFERROR(IF(A69<='EMI Calculator'!B7,C69*'EMI Calculator'!B6/12,""),"") | G69: =IFERROR(IF(A69<='EMI Calculator'!B7,MAX(C69-E69,0),""),"") | H69: =IFERROR(IF(A69<='EMI Calculator'!B7,H68+F69,""),"") | I69: =IFERROR(IF(A69<='EMI Calculator'!B7,I68+E69,""),"")
A70: 67 | B70: =IFERROR(DATE(YEAR(B69),MONTH(B69)+1,DAY(B69)),"") | C70: =IFERROR(IF(A70<='EMI Calculator'!B7,G69,""),"") | D70: =IFERROR(IF(A70<='EMI Calculator'!B7,'EMI Calculator'!B11,""),"") | E70: =IFERROR(IF(A70<='EMI Calculator'!B7,D70-F70,""),"") | F70: =IFERROR(IF(A70<='EMI Calculator'!B7,C70*'EMI Calculator'!B6/12,""),"") | G70: =IFERROR(IF(A70<='EMI Calculator'!B7,MAX(C70-E70,0),""),"") | H70: =IFERROR(IF(A70<='EMI Calculator'!B7,H69+F70,""),"") | I70: =IFERROR(IF(A70<='EMI Calculator'!B7,I69+E70,""),"")
A71: 68 | B71: =IFERROR(DATE(YEAR(B70),MONTH(B70)+1,DAY(B70)),"") | C71: =IFERROR(IF(A71<='EMI Calculator'!B7,G70,""),"") | D71: =IFERROR(IF(A71<='EMI Calculator'!B7,'EMI Calculator'!B11,""),"") | E71: =IFERROR(IF(A71<='EMI Calculator'!B7,D71-F71,""),"") | F71: =IFERROR(IF(A71<='EMI Calculator'!B7,C71*'EMI Calculator'!B6/12,""),"") | G71: =IFERROR(IF(A71<='EMI Calculator'!B7,MAX(C71-E71,0),""),"") | H71: =IFERROR(IF(A71<='EMI Calculator'!B7,H70+F71,""),"") | I71: =IFERROR(IF(A71<='EMI Calculator'!B7,I70+E71,""),"")
A72: 69 | B72: =IFERROR(DATE(YEAR(B71),MONTH(B71)+1,DAY(B71)),"") | C72: =IFERROR(IF(A72<='EMI Calculator'!B7,G71,""),"") | D72: =IFERROR(IF(A72<='EMI Calculator'!B7,'EMI Calculator'!B11,""),"") | E72: =IFERROR(IF(A72<='EMI Calculator'!B7,D72-F72,""),"") | F72: =IFERROR(IF(A72<='EMI Calculator'!B7,C72*'EMI Calculator'!B6/12,""),"") | G72: =IFERROR(IF(A72<='EMI Calculator'!B7,MAX(C72-E72,0),""),"") | H72: =IFERROR(IF(A72<='EMI Calculator'!B7,H71+F72,""),"") | I72: =IFERROR(IF(A72<='EMI Calculator'!B7,I71+E72,""),"")
A73: 70 | B73: =IFERROR(DATE(YEAR(B72),MONTH(B72)+1,DAY(B72)),"") | C73: =IFERROR(IF(A73<='EMI Calculator'!B7,G72,""),"") | D73: =IFERROR(IF(A73<='EMI Calculator'!B7,'EMI Calculator'!B11,""),"") | E73: =IFERROR(IF(A73<='EMI Calculator'!B7,D73-F73,""),"") | F73: =IFERROR(IF(A73<='EMI Calculator'!B7,C73*'EMI Calculator'!B6/12,""),"") | G73: =IFERROR(IF(A73<='EMI Calculator'!B7,MAX(C73-E73,0),""),"") | H73: =IFERROR(IF(A73<='EMI Calculator'!B7,H72+F73,""),"") | I73: =IFERROR(IF(A73<='EMI Calculator'!B7,I72+E73,""),"")
A74: 71 | B74: =IFERROR(DATE(YEAR(B73),MONTH(B73)+1,DAY(B73)),"") | C74: =IFERROR(IF(A74<='EMI Calculator'!B7,G73,""),"") | D74: =IFERROR(IF(A74<='EMI Calculator'!B7,'EMI Calculator'!B11,""),"") | E74: =IFERROR(IF(A74<='EMI Calculator'!B7,D74-F74,""),"") | F74: =IFERROR(IF(A74<='EMI Calculator'!B7,C74*'EMI Calculator'!B6/12,""),"") | G74: =IFERROR(IF(A74<='EMI Calculator'!B7,MAX(C74-E74,0),""),"") | H74: =IFERROR(IF(A74<='EMI Calculator'!B7,H73+F74,""),"") | I74: =IFERROR(IF(A74<='EMI Calculator'!B7,I73+E74,""),"")
A75: 72 | B75: =IFERROR(DATE(YEAR(B74),MONTH(B74)+1,DAY(B74)),"") | C75: =IFERROR(IF(A75<='EMI Calculator'!B7,G74,""),"") | D75: =IFERROR(IF(A75<='EMI Calculator'!B7,'EMI Calculator'!B11,""),"") | E75: =IFERROR(IF(A75<='EMI Calculator'!B7,D75-F75,""),"") | F75: =IFERROR(IF(A75<='EMI Calculator'!B7,C75*'EMI Calculator'!B6/12,""),"") | G75: =IFERROR(IF(A75<='EMI Calculator'!B7,MAX(C75-E75,0),""),"") | H75: =IFERROR(IF(A75<='EMI Calculator'!B7,H74+F75,""),"") | I75: =IFERROR(IF(A75<='EMI Calculator'!B7,I74+E75,""),"")
A76: 73 | B76: =IFERROR(DATE(YEAR(B75),MONTH(B75)+1,DAY(B75)),"") | C76: =IFERROR(IF(A76<='EMI Calculator'!B7,G75,""),"") | D76: =IFERROR(IF(A76<='EMI Calculator'!B7,'EMI Calculator'!B11,""),"") | E76: =IFERROR(IF(A76<='EMI Calculator'!B7,D76-F76,""),"") | F76: =IFERROR(IF(A76<='EMI Calculator'!B7,C76*'EMI Calculator'!B6/12,""),"") | G76: =IFERROR(IF(A76<='EMI Calculator'!B7,MAX(C76-E76,0),""),"") | H76: =IFERROR(IF(A76<='EMI Calculator'!B7,H75+F76,""),"") | I76: =IFERROR(IF(A76<='EMI Calculator'!B7,I75+E76,""),"")
A77: 74 | B77: =IFERROR(DATE(YEAR(B76),MONTH(B76)+1,DAY(B76)),"") | C77: =IFERROR(IF(A77<='EMI Calculator'!B7,G76,""),"") | D77: =IFERROR(IF(A77<='EMI Calculator'!B7,'EMI Calculator'!B11,""),"") | E77: =IFERROR(IF(A77<='EMI Calculator'!B7,D77-F77,""),"") | F77: =IFERROR(IF(A77<='EMI Calculator'!B7,C77*'EMI Calculator'!B6/12,""),"") | G77: =IFERROR(IF(A77<='EMI Calculator'!B7,MAX(C77-E77,0),""),"") | H77: =IFERROR(IF(A77<='EMI Calculator'!B7,H76+F77,""),"") | I77: =IFERROR(IF(A77<='EMI Calculator'!B7,I76+E77,""),"")
A78: 75 | B78: =IFERROR(DATE(YEAR(B77),MONTH(B77)+1,DAY(B77)),"") | C78: =IFERROR(IF(A78<='EMI Calculator'!B7,G77,""),"") | D78: =IFERROR(IF(A78<='EMI Calculator'!B7,'EMI Calculator'!B11,""),"") | E78: =IFERROR(IF(A78<='EMI Calculator'!B7,D78-F78,""),"") | F78: =IFERROR(IF(A78<='EMI Calculator'!B7,C78*'EMI Calculator'!B6/12,""),"") | G78: =IFERROR(IF(A78<='EMI Calculator'!B7,MAX(C78-E78,0),""),"") | H78: =IFERROR(IF(A78<='EMI Calculator'!B7,H77+F78,""),"") | I78: =IFERROR(IF(A78<='EMI Calculator'!B7,I77+E78,""),"")
A79: 76 | B79: =IFERROR(DATE(YEAR(B78),MONTH(B78)+1,DAY(B78)),"") | C79: =IFERROR(IF(A79<='EMI Calculator'!B7,G78,""),"") | D79: =IFERROR(IF(A79<='EMI Calculator'!B7,'EMI Calculator'!B11,""),"") | E79: =IFERROR(IF(A79<='EMI Calculator'!B7,D79-F79,""),"") | F79: =IFERROR(IF(A79<='EMI Calculator'!B7,C79*'EMI Calculator'!B6/12,""),"") | G79: =IFERROR(IF(A79<='EMI Calculator'!B7,MAX(C79-E79,0),""),"") | H79: =IFERROR(IF(A79<='EMI Calculator'!B7,H78+F79,""),"") | I79: =IFERROR(IF(A79<='EMI Calculator'!B7,I78+E79,""),"")
A80: 77 | B80: =IFERROR(DATE(YEAR(B79),MONTH(B79)+1,DAY(B79)),"") | C80: =IFERROR(IF(A80<='EMI Calculator'!B7,G79,""),"") | D80: =IFERROR(IF(A80<='EMI Calculator'!B7,'EMI Calculator'!B11,""),"") | E80: =IFERROR(IF(A80<='EMI Calculator'!B7,D80-F80,""),"") | F80: =IFERROR(IF(A80<='EMI Calculator'!B7,C80*'EMI Calculator'!B6/12,""),"") | G80: =IFERROR(IF(A80<='EMI Calculator'!B7,MAX(C80-E80,0),""),"") | H80: =IFERROR(IF(A80<='EMI Calculator'!B7,H79+F80,""),"") | I80: =IFERROR(IF(A80<='EMI Calculator'!B7,I79+E80,""),"")
A81: 78 | B81: =IFERROR(DATE(YEAR(B80),MONTH(B80)+1,DAY(B80)),"") | C81: =IFERROR(IF(A81<='EMI Calculator'!B7,G80,""),"") | D81: =IFERROR(IF(A81<='EMI Calculator'!B7,'EMI Calculator'!B11,""),"") | E81: =IFERROR(IF(A81<='EMI Calculator'!B7,D81-F81,""),"") | F81: =IFERROR(IF(A81<='EMI Calculator'!B7,C81*'EMI Calculator'!B6/12,""),"") | G81: =IFERROR(IF(A81<='EMI Calculator'!B7,MAX(C81-E81,0),""),"") | H81: =IFERROR(IF(A81<='EMI Calculator'!B7,H80+F81,""),"") | I81: =IFERROR(IF(A81<='EMI Calculator'!B7,I80+E81,""),"")
A82: 79 | B82: =IFERROR(DATE(YEAR(B81),MONTH(B81)+1,DAY(B81)),"") | C82: =IFERROR(IF(A82<='EMI Calculator'!B7,G81,""),"") | D82: =IFERROR(IF(A82<='EMI Calculator'!B7,'EMI Calculator'!B11,""),"") | E82: =IFERROR(IF(A82<='EMI Calculator'!B7,D82-F82,""),"") | F82: =IFERROR(IF(A82<='EMI Calculator'!B7,C82*'EMI Calculator'!B6/12,""),"") | G82: =IFERROR(IF(A82<='EMI Calculator'!B7,MAX(C82-E82,0),""),"") | H82: =IFERROR(IF(A82<='EMI Calculator'!B7,H81+F82,""),"") | I82: =IFERROR(IF(A82<='EMI Calculator'!B7,I81+E82,""),"")
A83: 80 | B83: =IFERROR(DATE(YEAR(B82),MONTH(B82)+1,DAY(B82)),"") | C83: =IFERROR(IF(A83<='EMI Calculator'!B7,G82,""),"") | D83: =IFERROR(IF(A83<='EMI Calculator'!B7,'EMI Calculator'!B11,""),"") | E83: =IFERROR(IF(A83<='EMI Calculator'!B7,D83-F83,""),"") | F83: =IFERROR(IF(A83<='EMI Calculator'!B7,C83*'EMI Calculator'!B6/12,""),"") | G83: =IFERROR(IF(A83<='EMI Calculator'!B7,MAX(C83-E83,0),""),"") | H83: =IFERROR(IF(A83<='EMI Calculator'!B7,H82+F83,""),"") | I83: =IFERROR(IF(A83<='EMI Calculator'!B7,I82+E83,""),"")
A84: 81 | B84: =IFERROR(DATE(YEAR(B83),MONTH(B83)+1,DAY(B83)),"") | C84: =IFERROR(IF(A84<='EMI Calculator'!B7,G83,""),"") | D84: =IFERROR(IF(A84<='EMI Calculator'!B7,'EMI Calculator'!B11,""),"") | E84: =IFERROR(IF(A84<='EMI Calculator'!B7,D84-F84,""),"") | F84: =IFERROR(IF(A84<='EMI Calculator'!B7,C84*'EMI Calculator'!B6/12,""),"") | G84: =IFERROR(IF(A84<='EMI Calculator'!B7,MAX(C84-E84,0),""),"") | H84: =IFERROR(IF(A84<='EMI Calculator'!B7,H83+F84,""),"") | I84: =IFERROR(IF(A84<='EMI Calculator'!B7,I83+E84,""),"")
A85: 82 | B85: =IFERROR(DATE(YEAR(B84),MONTH(B84)+1,DAY(B84)),"") | C85: =IFERROR(IF(A85<='EMI Calculator'!B7,G84,""),"") | D85: =IFERROR(IF(A85<='EMI Calculator'!B7,'EMI Calculator'!B11,""),"") | E85: =IFERROR(IF(A85<='EMI Calculator'!B7,D85-F85,""),"") | F85: =IFERROR(IF(A85<='EMI Calculator'!B7,C85*'EMI Calculator'!B6/12,""),"") | G85: =IFERROR(IF(A85<='EMI Calculator'!B7,MAX(C85-E85,0),""),"") | H85: =IFERROR(IF(A85<='EMI Calculator'!B7,H84+F85,""),"") | I85: =IFERROR(IF(A85<='EMI Calculator'!B7,I84+E85,""),"")
A86: 83 | B86: =IFERROR(DATE(YEAR(B85),MONTH(B85)+1,DAY(B85)),"") | C86: =IFERROR(IF(A86<='EMI Calculator'!B7,G85,""),"") | D86: =IFERROR(IF(A86<='EMI Calculator'!B7,'EMI Calculator'!B11,""),"") | E86: =IFERROR(IF(A86<='EMI Calculator'!B7,D86-F86,""),"") | F86: =IFERROR(IF(A86<='EMI Calculator'!B7,C86*'EMI Calculator'!B6/12,""),"") | G86: =IFERROR(IF(A86<='EMI Calculator'!B7,MAX(C86-E86,0),""),"") | H86: =IFERROR(IF(A86<='EMI Calculator'!B7,H85+F86,""),"") | I86: =IFERROR(IF(A86<='EMI Calculator'!B7,I85+E86,""),"")
A87: 84 | B87: =IFERROR(DATE(YEAR(B86),MONTH(B86)+1,DAY(B86)),"") | C87: =IFERROR(IF(A87<='EMI Calculator'!B7,G86,""),"") | D87: =IFERROR(IF(A87<='EMI Calculator'!B7,'EMI Calculator'!B11,""),"") | E87: =IFERROR(IF(A87<='EMI Calculator'!B7,D87-F87,""),"") | F87: =IFERROR(IF(A87<='EMI Calculator'!B7,C87*'EMI Calculator'!B6/12,""),"") | G87: =IFERROR(IF(A87<='EMI Calculator'!B7,MAX(C87-E87,0),""),"") | H87: =IFERROR(IF(A87<='EMI Calculator'!B7,H86+F87,""),"") | I87: =IFERROR(IF(A87<='EMI Calculator'!B7,I86+E87,""),"")
A88: 85 | B88: =IFERROR(DATE(YEAR(B87),MONTH(B87)+1,DAY(B87)),"") | C88: =IFERROR(IF(A88<='EMI Calculator'!B7,G87,""),"") | D88: =IFERROR(IF(A88<='EMI Calculator'!B7,'EMI Calculator'!B11,""),"") | E88: =IFERROR(IF(A88<='EMI Calculator'!B7,D88-F88,""),"") | F88: =IFERROR(IF(A88<='EMI Calculator'!B7,C88*'EMI Calculator'!B6/12,""),"") | G88: =IFERROR(IF(A88<='EMI Calculator'!B7,MAX(C88-E88,0),""),"") | H88: =IFERROR(IF(A88<='EMI Calculator'!B7,H87+F88,""),"") | I88: =IFERROR(IF(A88<='EMI Calculator'!B7,I87+E88,""),"")
A89: 86 | B89: =IFERROR(DATE(YEAR(B88),MONTH(B88)+1,DAY(B88)),"") | C89: =IFERROR(IF(A89<='EMI Calculator'!B7,G88,""),"") | D89: =IFERROR(IF(A89<='EMI Calculator'!B7,'EMI Calculator'!B11,""),"") | E89: =IFERROR(IF(A89<='EMI Calculator'!B7,D89-F89,""),"") | F89: =IFERROR(IF(A89<='EMI Calculator'!B7,C89*'EMI Calculator'!B6/12,""),"") | G89: =IFERROR(IF(A89<='EMI Calculator'!B7,MAX(C89-E89,0),""),"") | H89: =IFERROR(IF(A89<='EMI Calculator'!B7,H88+F89,""),"") | I89: =IFERROR(IF(A89<='EMI Calculator'!B7,I88+E89,""),"")
A90: 87 | B90: =IFERROR(DATE(YEAR(B89),MONTH(B89)+1,DAY(B89)),"") | C90: =IFERROR(IF(A90<='EMI Calculator'!B7,G89,""),"") | D90: =IFERROR(IF(A90<='EMI Calculator'!B7,'EMI Calculator'!B11,""),"") | E90: =IFERROR(IF(A90<='EMI Calculator'!B7,D90-F90,""),"") | F90: =IFERROR(IF(A90<='EMI Calculator'!B7,C90*'EMI Calculator'!B6/12,""),"") | G90: =IFERROR(IF(A90<='EMI Calculator'!B7,MAX(C90-E90,0),""),"") | H90: =IFERROR(IF(A90<='EMI Calculator'!B7,H89+F90,""),"") | I90: =IFERROR(IF(A90<='EMI Calculator'!B7,I89+E90,""),"")
A91: 88 | B91: =IFERROR(DATE(YEAR(B90),MONTH(B90)+1,DAY(B90)),"") | C91: =IFERROR(IF(A91<='EMI Calculator'!B7,G90,""),"") | D91: =IFERROR(IF(A91<='EMI Calculator'!B7,'EMI Calculator'!B11,""),"") | E91: =IFERROR(IF(A91<='EMI Calculator'!B7,D91-F91,""),"") | F91: =IFERROR(IF(A91<='EMI Calculator'!B7,C91*'EMI Calculator'!B6/12,""),"") | G91: =IFERROR(IF(A91<='EMI Calculator'!B7,MAX(C91-E91,0),""),"") | H91: =IFERROR(IF(A91<='EMI Calculator'!B7,H90+F91,""),"") | I91: =IFERROR(IF(A91<='EMI Calculator'!B7,I90+E91,""),"")
A92: 89 | B92: =IFERROR(DATE(YEAR(B91),MONTH(B91)+1,DAY(B91)),"") | C92: =IFERROR(IF(A92<='EMI Calculator'!B7,G91,""),"") | D92: =IFERROR(IF(A92<='EMI Calculator'!B7,'EMI Calculator'!B11,""),"") | E92: =IFERROR(IF(A92<='EMI Calculator'!B7,D92-F92,""),"") | F92: =IFERROR(IF(A92<='EMI Calculator'!B7,C92*'EMI Calculator'!B6/12,""),"") | G92: =IFERROR(IF(A92<='EMI Calculator'!B7,MAX(C92-E92,0),""),"") | H92: =IFERROR(IF(A92<='EMI Calculator'!B7,H91+F92,""),"") | I92: =IFERROR(IF(A92<='EMI Calculator'!B7,I91+E92,""),"")
A93: 90 | B93: =IFERROR(DATE(YEAR(B92),MONTH(B92)+1,DAY(B92)),"") | C93: =IFERROR(IF(A93<='EMI Calculator'!B7,G92,""),"") | D93: =IFERROR(IF(A93<='EMI Calculator'!B7,'EMI Calculator'!B11,""),"") | E93: =IFERROR(IF(A93<='EMI Calculator'!B7,D93-F93,""),"") | F93: =IFERROR(IF(A93<='EMI Calculator'!B7,C93*'EMI Calculator'!B6/12,""),"") | G93: =IFERROR(IF(A93<='EMI Calculator'!B7,MAX(C93-E93,0),""),"") | H93: =IFERROR(IF(A93<='EMI Calculator'!B7,H92+F93,""),"") | I93: =IFERROR(IF(A93<='EMI Calculator'!B7,I92+E93,""),"")
A94: 91 | B94: =IFERROR(DATE(YEAR(B93),MONTH(B93)+1,DAY(B93)),"") | C94: =IFERROR(IF(A94<='EMI Calculator'!B7,G93,""),"") | D94: =IFERROR(IF(A94<='EMI Calculator'!B7,'EMI Calculator'!B11,""),"") | E94: =IFERROR(IF(A94<='EMI Calculator'!B7,D94-F94,""),"") | F94: =IFERROR(IF(A94<='EMI Calculator'!B7,C94*'EMI Calculator'!B6/12,""),"") | G94: =IFERROR(IF(A94<='EMI Calculator'!B7,MAX(C94-E94,0),""),"") | H94: =IFERROR(IF(A94<='EMI Calculator'!B7,H93+F94,""),"") | I94: =IFERROR(IF(A94<='EMI Calculator'!B7,I93+E94,""),"")
A95: 92 | B95: =IFERROR(DATE(YEAR(B94),MONTH(B94)+1,DAY(B94)),"") | C95: =IFERROR(IF(A95<='EMI Calculator'!B7,G94,""),"") | D95: =IFERROR(IF(A95<='EMI Calculator'!B7,'EMI Calculator'!B11,""),"") | E95: =IFERROR(IF(A95<='EMI Calculator'!B7,D95-F95,""),"") | F95: =IFERROR(IF(A95<='EMI Calculator'!B7,C95*'EMI Calculator'!B6/12,""),"") | G95: =IFERROR(IF(A95<='EMI Calculator'!B7,MAX(C95-E95,0),""),"") | H95: =IFERROR(IF(A95<='EMI Calculator'!B7,H94+F95,""),"") | I95: =IFERROR(IF(A95<='EMI Calculator'!B7,I94+E95,""),"")
A96: 93 | B96: =IFERROR(DATE(YEAR(B95),MONTH(B95)+1,DAY(B95)),"") | C96: =IFERROR(IF(A96<='EMI Calculator'!B7,G95,""),"") | D96: =IFERROR(IF(A96<='EMI Calculator'!B7,'EMI Calculator'!B11,""),"") | E96: =IFERROR(IF(A96<='EMI Calculator'!B7,D96-F96,""),"") | F96: =IFERROR(IF(A96<='EMI Calculator'!B7,C96*'EMI Calculator'!B6/12,""),"") | G96: =IFERROR(IF(A96<='EMI Calculator'!B7,MAX(C96-E96,0),""),"") | H96: =IFERROR(IF(A96<='EMI Calculator'!B7,H95+F96,""),"") | I96: =IFERROR(IF(A96<='EMI Calculator'!B7,I95+E96,""),"")
A97: 94 | B97: =IFERROR(DATE(YEAR(B96),MONTH(B96)+1,DAY(B96)),"") | C97: =IFERROR(IF(A97<='EMI Calculator'!B7,G96,""),"") | D97: =IFERROR(IF(A97<='EMI Calculator'!B7,'EMI Calculator'!B11,""),"") | E97: =IFERROR(IF(A97<='EMI Calculator'!B7,D97-F97,""),"") | F97: =IFERROR(IF(A97<='EMI Calculator'!B7,C97*'EMI Calculator'!B6/12,""),"") | G97: =IFERROR(IF(A97<='EMI Calculator'!B7,MAX(C97-E97,0),""),"") | H97: =IFERROR(IF(A97<='EMI Calculator'!B7,H96+F97,""),"") | I97: =IFERROR(IF(A97<='EMI Calculator'!B7,I96+E97,""),"")
A98: 95 | B98: =IFERROR(DATE(YEAR(B97),MONTH(B97)+1,DAY(B97)),"") | C98: =IFERROR(IF(A98<='EMI Calculator'!B7,G97,""),"") | D98: =IFERROR(IF(A98<='EMI Calculator'!B7,'EMI Calculator'!B11,""),"") | E98: =IFERROR(IF(A98<='EMI Calculator'!B7,D98-F98,""),"") | F98: =IFERROR(IF(A98<='EMI Calculator'!B7,C98*'EMI Calculator'!B6/12,""),"") | G98: =IFERROR(IF(A98<='EMI Calculator'!B7,MAX(C98-E98,0),""),"") | H98: =IFERROR(IF(A98<='EMI Calculator'!B7,H97+F98,""),"") | I98: =IFERROR(IF(A98<='EMI Calculator'!B7,I97+E98,""),"")
A99: 96 | B99: =IFERROR(DATE(YEAR(B98),MONTH(B98)+1,DAY(B98)),"") | C99: =IFERROR(IF(A99<='EMI Calculator'!B7,G98,""),"") | D99: =IFERROR(IF(A99<='EMI Calculator'!B7,'EMI Calculator'!B11,""),"") | E99: =IFERROR(IF(A99<='EMI Calculator'!B7,D99-F99,""),"") | F99: =IFERROR(IF(A99<='EMI Calculator'!B7,C99*'EMI Calculator'!B6/12,""),"") | G99: =IFERROR(IF(A99<='EMI Calculator'!B7,MAX(C99-E99,0),""),"") | H99: =IFERROR(IF(A99<='EMI Calculator'!B7,H98+F99,""),"") | I99: =IFERROR(IF(A99<='EMI Calculator'!B7,I98+E99,""),"")
A100: 97 | B100: =IFERROR(DATE(YEAR(B99),MONTH(B99)+1,DAY(B99)),"") | C100: =IFERROR(IF(A100<='EMI Calculator'!B7,G99,""),"") | D100: =IFERROR(IF(A100<='EMI Calculator'!B7,'EMI Calculator'!B11,""),"") | E100: =IFERROR(IF(A100<='EMI Calculator'!B7,D100-F100,""),"") | F100: =IFERROR(IF(A100<='EMI Calculator'!B7,C100*'EMI Calculator'!B6/12,""),"") | G100: =IFERROR(IF(A100<='EMI Calculator'!B7,MAX(C100-E100,0),""),"") | H100: =IFERROR(IF(A100<='EMI Calculator'!B7,H99+F100,""),"") | I100: =IFERROR(IF(A100<='EMI Calculator'!B7,I99+E100,""),"")
A101: 98 | B101: =IFERROR(DATE(YEAR(B100),MONTH(B100)+1,DAY(B100)),"") | C101: =IFERROR(IF(A101<='EMI Calculator'!B7,G100,""),"") | D101: =IFERROR(IF(A101<='EMI Calculator'!B7,'EMI Calculator'!B11,""),"") | E101: =IFERROR(IF(A101<='EMI Calculator'!B7,D101-F101,""),"") | F101: =IFERROR(IF(A101<='EMI Calculator'!B7,C101*'EMI Calculator'!B6/12,""),"") | G101: =IFERROR(IF(A101<='EMI Calculator'!B7,MAX(C101-E101,0),""),"") | H101: =IFERROR(IF(A101<='EMI Calculator'!B7,H100+F101,""),"") | I101: =IFERROR(IF(A101<='EMI Calculator'!B7,I100+E101,""),"")
...
